Workbook

Sheet instrucciones
A1: Validación de requerimientos del sistema de información de Escaneo de Horizonte
A3: Propósito | B3: Registrar el concepto del equipo técnico del IETS sobre cada requerimiento funcional y no funcional de la especificación oficial, como insumo de la segunda entrega del cronograma: requerimientos aprobados, con fecha 11 de septiembre de 2026.
A4: Documentos base | B4: Especificaciones-tecnicas-plataforma-EH_IETS_2026_V1.pdf (RF01 a RF20, matriz de criterios P1 a P6 y requerimientos no funcionales) y Cronograma_Desarrollo_SI_Escaneo_Horizonte.xlsx (79 días hábiles, nueve entregas).
A5: Quién diligencia | B5: La coordinación metodológica de Escaneo de Horizonte emite el concepto funcional; el líder técnico del componente de desarrollo emite el concepto de factibilidad. Cuando difieran, prima el registro de la observación sobre el acuerdo aparente.
A6: Hojas del libro | B6: requerimientos: los 20 RF más los 6 criterios de priorización. no_funcionales: los requerimientos no funcionales y transversales. resumen: conteos automáticos. control de cambios: versionamiento y firmas.
A7: Celdas de captura | B7: Las celdas con fondo amarillo son las únicas que se diligencian. El resto es información de contexto y no debe modificarse.
A9: Significado de cada concepto
A10: Viable | B10: El requerimiento se puede construir tal como está enunciado, dentro del alcance, el plazo y el equipo previstos en el cronograma. No requiere decisión adicional de negocio ni gestión externa.
A11: Inviable | B11: No se puede construir en este componente. Se marca así cuando depende de un dato, un permiso o una integración que no está disponible y no se puede resolver dentro del plazo, o cuando excede el alcance contratado. Exige justificación en observaciones.
A12: Replantear | B12: El objetivo del requerimiento es válido pero su enunciado actual no es implementable como está: hay ambigüedad, contradicción entre secciones de la especificación, o una ruta técnica distinta que lo cumple mejor. Exige propuesta concreta en observaciones.
A13: Observaciones | B13: Campo obligatorio para inviable y replantear; opcional para viable. Debe indicar el hecho que sustenta el concepto, no una opinión general.
A15: Advertencia sobre la columna de estado
A16: Lectura previa | B16: La columna «Estado en el prototipo» refleja lo que ya existe en la versión de trabajo del sistema. Es contexto, no un concepto emitido: que algo esté construido no lo hace viable para producción, y que no exista no lo hace inviable. El concepto se emite sobre el requerimiento de la especificación, no sobre el prototipo.

Sheet requerimientos
A1: Requerimientos funcionales y criterios de priorización: concepto de viabilidad
A2: Las columnas con fondo amarillo son las de captura. Concepto y observaciones son obligatorios para cada fila antes de la entrega de requerimientos aprobados.
A4: No | B4: Módulo | C4: ID | D4: Requerimiento | E4: Descripción y alcance según la especificación | F4: Entrega | G4: Actividad del cronograma | H4: Estado en el prototipo | I4: Prioridad | J4: Concepto | K4: Observaciones | L4: Responsable del concepto | M4: Fecha
A5: 1 | B5: M0 | C5: RF01 | D5: Captura proactiva automatizada por APIs y Webscraping y conectores | E5: Conectores y tareas programadas hacia registros de ensayos clínicos (ClinicalTrials.gov, WHO ICTRP) filtrando fases II, III y IV, agencias regulatorias (FDA, EMA) y redes internacionales (EuroScan i-HTS). La especificación deja pendiente confirmar las fuentes y rutas. | F5: 4 | G5: Sprint 2, actividad 30: motor de vigilancia automatizada | H5: Adaptadores clinicaltrials, fda, ema, pubmed y who_ictrp registrados; WHO ICTRP opera por lote | I5: Imprescindible | J5: Viable | K5: En caso de que la arquitectura del sitio web sea compleja, tenga captcha, o cambie. Se debera tener en cuenta una opción de diligenciamiento manual.
A6: 2 | B6: M0 | C6: RF02 | D6: Captura reactiva mediante portal web de postulación | E6: Interfaz pública o con autenticación ligera para que sociedades científicas, pacientes, academia e industria postulen tecnologías. Campos obligatorios: nombre comercial y DCI, mecanismo, fabricante, indicación, fase, evidencia y declaración de conflicto de interés. | F6: 4 | G6: Sprint 2, actividad 30 | H6: Portal público operando con conflicto de interés bloqueante y cola de moderación; sin reCAPTCHA en producción | I6: Deseable | J6: Viable | K6: Viable como micrositio de consulta externa
A7: 3 | B7: M0 | C7: RF03 | D7: Repositorio de acopio preliminar (staging data lake) | E7: Persistencia de toda señal capturada con estado Capturada / No asignada y metadatos de auditoría: fecha y hora de captura, fuente de origen indicando canal proactivo o reactivo, y usuario o proceso que ejecutó la ingesta. | F7: 4 | G7: Sprint 1, actividad 27 y sprint 2, actividad 31 | H7: Tabla de crudos por conector e identificador externo; permite reprocesar sin volver a la fuente | I7: Imprescindible | J7: Viable | K7: Necesario realizar una validación
A8: 4 | B8: M0 | C8: RF04 | D8: Buzón de entrada y previsualización | E8: Bandeja donde el evaluador técnico visualiza, filtra por fecha o fuente y selecciona lotes de tecnologías acopiadas para transferirlas al ciclo formal. | F8: 4 | G8: Sprint 2, actividad 31 | H8: Filtro por canal, vista previa del crudo y transferencia por lotes | I8: Importante | J8: Viable | K8: Necesario realizar una validación, revisar validación de IA y UX/UI con base a parametros definidos
A9: 5 | B9: M1 | C9: RF05 | D9: Parametrización del ciclo operativo | E9: Creación de ciclos con código, fecha de apertura, fecha de corte de datos, fecha proyectada de boletín y cinco estados. Regla de tres ciclos al año con ventana de 10 a 16 semanas, conforme a la sección 10 del manual. | F9: 4 | G9: Sprint 1, actividad 25: núcleo del backend | H9: Implementado con validación de la regla de negocio y máquina de estados | I9: Imprescindible | J9: Viable | K9: Parametrización fija, o se le puden adicionar o cambiar
A10: 6 | B10: M1 | C10: RF06 | D10: Taxonomía oficial de los seis clústeres de salud | E10: Tipificación obligatoria en cáncer, alto costo, huérfanas o raras, Covid-19 e infecciosas emergentes, prevalentes y otras prioritarias. La especificación advierte que puede variar según referenciación. | F10: 4 | G10: Sprint 1, actividad 25 | H10: Catálogo parametrizable con sugerencia asistida por CIE-10 y MeSH | I10: Imprescindible | J10: Viable | K10: Parametrización fija, o se le puden adicionar o cambiar
A11: 7 | B11: M1 | C11: RF07 | D11: Clasificación por las siete tipologías tecnológicas | E11: Medicamento químico o biológico, terapias avanzadas y génicas, dispositivos médicos, diagnóstico in vitro, procedimientos quirúrgicos, salud digital y algoritmos de inteligencia artificial. | F11: 4 | G11: Sprint 1, actividad 25 | H11: Catálogo parametrizable con mapeo de los cuatro tipos heredados | I11: Imprescindible | J11: Viable | K11: Parametrización fija, o se le puden adicionar o cambiar
A12: 8 | B12: M1 | C12: RF08 | D12: Asignación y arrastre de señales al ciclo activo | E12: Selección de tecnologías del repositorio de acopio y asociación formal al ciclo, con su clúster y tipología, cambiando el estado a Asignada a ciclo. | F12: 4 | G12: Sprint 1, actividad 27 | H12: Transferencia por lotes desde la bandeja, auditada | I12: Importante | J12: Replantear | K12: Necesario ampliar la busqueda y configuración de OCR activo
A13: 9 | B13: M2 | C13: RF09 | D13: Motor algorítmico de desduplicación inteligente | E13: Identificación y fusión de registros idénticos de múltiples fuentes comparando nombre comercial, DCI, número de ensayo clínico y fabricante, con matching difuso y umbral de similitud del 85 por ciento. | F13: 5 | G13: Sprint 3, actividad 39: criterios de filtrado | H13: Motor difuso operando; la fusión siempre la confirma un evaluador | I13: Imprescindible | J13: Viable | K13: Revisarlo y validarlo (posiblidad de hacerlo internamente)
A14: 10 | B14: M2 | C14: RF10 | D14: Criterio de novedad e innovación | E14: Lista de verificación de cuatro vías: nueva entidad química o biológica, nueva indicación relevante, dispositivo de clase de riesgo alta o disruptivo, algoritmo de inteligencia artificial con nuevo soporte diagnóstico. Las modificaciones menores se catalogan como excluidas. | F14: 5 | G14: Sprint 3, actividad 39 | H14: Catálogo de vías editable sin desplegar | I14: Importante | J14: Viable | K14: Parametrización fija, o se le puden adicionar o cambiar
A15: 11 | B15: M2 | C15: RF11 | D15: Verificación regulatoria ante INVIMA | E15: Contraste del principio activo o dispositivo contra los registros sanitarios vigentes del INVIMA y contra los conceptos de la sala especializada. Solo se acepta como emergente si no cuenta con registro, o si se trata de indicación nueva, forma farmacéutica disruptiva o combinación. | F15: 5 | G15: Sprint 3, actividad 39 | H15: Índice local con sincronización desde datos abiertos y contingencia por archivo plano; el cruce por principio activo sigue degradado | I15: Deseable | J15: Replantear | K15: Necesario ampliar el requerimiento
A16: 12 | B16: M2 | C16: RF12 | D16: Consolidación del Listado Único depurado | E16: Salida consolidada por clúster. Lo que supera el filtro avanza en estado Filtrada / Apta para priorización; lo descartado pasa a Excluida con registro obligatorio del motivo. | F16: 5 | G16: Sprint 3, actividad 39 | H16: Listado por clúster con exportación | I16: Importante | J16: Viable | K16: Validarlo
... A24: 20 | B24: M4 | C24: RF13 | D24: Editor estructurado de fichas de tecnologías emergentes | E24: Formulario con resumen de la condición, mecanismo biológico o tecnológico, población objetivo en Colombia, estado del arte de la evidencia, comparadores en el SGSSS y riesgos de adopción. | F24: 5 | G24: Sprint 3, actividad 40: fichas técnicas | H24: Tres niveles de producto documental; editor estructurado, sin editor enriquecido | I24: Importante | J24: Viable | K24: Validarlo
A25: 21 | B25: M4 | C25: RF14 | D25: Editor de informes en profundidad (Mini-HTA) | E25: Pregunta PICO estructurada, modelación preliminar del impacto presupuestario a uno a tres años y análisis de incertidumbre clínica. La especificación deja pendiente qué tecnologías lo ameritan y su ruta de activación según diálogos tempranos. | F25: 6 | G25: Sprint 3, actividad 40 y sprint 4 | H25: Nivel sugerido por puntaje, sobreescribible; criterio de activación aún abierto | I25: Fuera de alcance | J25: Viable
A26: 22 | B26: M4 | C26: RF15 | D26: Workflow de revisión por pares | E26: Seis estados editoriales: borrador, revisión interna de calidad, revisión externa por pares, con observaciones, aprobado por comité técnico y publicado en plataforma. | F26: 6 | G26: Sprint 4 | H26: Los seis estados operan y quedan auditados | I26: Fuera de alcance | J26: Viable
A27: 23 | B27: M4 | C27: RF16 | D27: Portal de revisores externos y conflicto de interés | E27: Credenciales temporales para expertos externos, acceso de solo lectura al informe asignado, formulario digital obligatorio de conflicto de interés y observaciones técnicas estructuradas. | F27: 6 | G27: Sprint 4 | H27: Token de 10 días sin cuenta; sin envío por correo institucional | I27: Fuera de alcance | J27: Viable
A28: 24 | B28: M5 | C28: RF17 | D28: Dashboard interactivo de gobernanza anticipatoria | E28: Filtros por clúster, tipología, fase clínica, nivel de priorización y rango de fechas. Cuatro visualizaciones obligatorias: distribución por clúster, dispersión de tiempo al mercado, mapa de calor de impacto presupuestal y embudo de conversión del ciclo. | F28: 6 | G28: Sprint 4, actividad 43: tableros analíticos | H28: Tablero completo con capa pública y capa restringida; franjas de tiempo al mercado parametrizadas | I28: Imprescindible | J28: Viable
A29: 25 | B29: M5 | C29: RF18 | D29: Ficha pública e interfaz de consulta rápida | E29: Buscador avanzado para funcionarios del MSPS e INVIMA, con expediente completo, descarga de la ficha en PDF y visualización de los ensayos clínicos asociados. | F29: 6 | G29: Sprint 4, actividad 43 | H29: Expedientes publicados y no confidenciales, sin datos presupuestales; exportación en HTML institucional | I29: Deseable | J29: Viable
A30: 26 | B30: M5 | C30: RF19 | D30: Generador automatizado de boletines trimestrales | E30: Compilación automática del Boletín Epidemiológico y Financiero de Tecnologías Emergentes con maquetación ejecutiva para alta dirección. | F30: 6 | G30: Sprint 4, actividad 44: boletines y reportes | H30: Se compila al cerrar el ciclo y queda pendiente de aprobación del líder; PDF nativo pendiente | I30: Fuera de alcance | J30: Replantear
A31: 27 | B31: M5 | C31: RF20 | D31: Sistema de alertas tempranas | E31: Notificaciones configurables cuando una tecnología de alto riesgo presupuestal cambia de fase o cuando se detecta un nuevo ensayo fase III en el país. | F31: 6 | G31: Sprint 4, actividad 46: tareas automáticas y notificaciones | H31: Alertas dentro de la plataforma; sin correo institucional | I31: Deseable | J31: Viable

Sheet no_funcionales
A1: Requerimientos no funcionales y transversales: concepto de viabilidad
A2: Las columnas con fondo amarillo son las de captura. Concepto y observaciones son obligatorios para cada fila antes de la entrega de requerimientos aprobados.
A4: No | B4: Categoría | C4: ID | D4: Requerimiento | E4: Descripción y alcance según la especificación | F4: Entrega | G4: Actividad del cronograma | H4: Estado en el prototipo | I4: Prioridad | J4: Concepto | K4: Observaciones | L4: Responsable del concepto | M4: Fecha
A5: 1 | B5: Trazabilidad | C5: RNF01 | D5: Bitácora inmutable de auditoría | E5: Cada inserción, cambio de estado, modificación de puntaje o descarte genera un registro inmutable con identificador de usuario, dirección IP, fecha y hora UTC, valor anterior y valor nuevo. No puede ser modificado ni borrado por ningún usuario, incluido el administrador. | F5: 7 | G5: Actividad 25 y actividad 51 | H5: Bitácora append-only con listener y middleware | I5: Imprescindible | J5: Viable
A6: 2 | B6: Seguridad | C6: RNF02 | D6: Control de acceso basado en roles de cinco perfiles | E6: SuperAdmin o líder, evaluador técnico, evaluador clínico, revisor por pares y tomador de decisiones, con permisos por módulo y a nivel de campo para los criterios P1 a P6. | F6: 4 | G6: Actividad 19 y actividad 26 | H6: Veinte permisos declarativos con granularidad por criterio | I6: Imprescindible | J6: Viable
A7: 3 | B7: Seguridad | C7: RNF03 | D7: Cifrado en tránsito y en reposo | E7: Comunicación bajo HTTPS con TLS 1.3 y certificados válidos. Datos sensibles, incluidas evaluaciones preliminares e información bajo acuerdo de confidencialidad con desarrolladores, cifrados en reposo con AES-256. | F7: 8 | G7: Actividad 51: pruebas de seguridad y actividad 55 | H7: Marca de confidencialidad por documento; cifrado en reposo pendiente del ambiente productivo | I7: Imprescindible | J7: Viable
A8: 4 | B8: Desempeño | C8: RNF04 | D8: Disponibilidad mínima del 99,5 por ciento en horario laboral | E8: Arquitectura, respaldo y monitoreo que sostengan el nivel de servicio comprometido. | F8: 8 | G8: Actividad 55 y actividad 61 | H8: Pendiente: depende del ambiente institucional de despliegue | I8: Imprescindible | J8: Viable
A9: 5 | B9: Desempeño | C9: RNF05 | D9: Tiempo de respuesta bajo dos segundos en el percentil 95 | E9: Las pantallas de consulta responden por debajo de dos segundos en el 95 por ciento de las peticiones. | F9: 7 | G9: Actividad 51: pruebas de desempeño y carga | H9: Cumple en pruebas locales; margen estrecho en el índice regulatorio a escala completa | I9: Deseable | J9: Inviable
A10: 6 | B10: Interoperabilidad | C10: RNF06 | D10: Endpoints seguros con OAuth2 para cooperación internacional | E10: Interoperabilidad con EuroScan i-HTS, el Innovation Observatory del Reino Unido y CONETEC de Argentina. | F10: 9 | G10: Actividad 58 y actividad 59 | H10: Pendiente: requiere convenio institucional previo | I10: Imprescindible | J10: Viable
A11: 7 | B11: Arquitectura | C11: RNF07 | D11: Base de datos relacional y documental | E11: PostgreSQL con JSONB para el crudo de ingesta y pgvector para recuperación semántica, más vistas materializadas para la analítica. | F11: 4 | G11: Actividad 18: modelado de la base de datos | H11: Código agnóstico del motor; la migración a PostgreSQL no se ha ejecutado en producción | I11: Imprescindible | J11: Viable
A12: 8 | B12: Arquitectura | C12: RNF08 | D12: Motor de tareas asíncronas | E12: La extracción de fuentes externas no bloquea el hilo de la aplicación web, con cola de trabajos, reintento exponencial y respeto de los límites de peticiones de cada fuente. | F12: 5 | G12: Actividad 46: programación de tareas automáticas | H12: Cola con reanudación dentro del mismo proceso; sin cola externa | I12: Imprescindible | J12: Viable
A13: 9 | B13: Operación | C13: RNF09 | D13: Contenerización y canalización de integración y despliegue continuo | E13: Empaquetado en contenedores y canalización con pruebas unitarias automatizadas para los algoritmos de priorización. | F13: 3 | G13: Actividad 16 y actividad 21 | H13: Pendiente: hoy no hay contenedores ni canalización | I13: Importante | J13: Viable
A14: 10 | B14: Operación | C14: RNF10 | D14: Migraciones versionadas del esquema | E14: Control de versiones del esquema con posibilidad de reversión. | F14: 3 | G14: Actividad 18 | H14: Pendiente: hoy operan migraciones idempotentes sin versionar | I14: Importante | J14: Viable
A15: 11 | B15: Documentación | C15: RNF11 | D15: Documentación interactiva OpenAPI actualizada automáticamente | E15: Facilita la integración futura con otros sistemas del Ministerio de Salud o del INVIMA. | F15: 9 | G15: Actividad 58: manual técnico | H15: Documentación generada por el marco de trabajo; falta publicarla formalmente | I15: Importante | J15: Viable
A16: 12 | B16: Seguridad | C16: RNF12 | D16: Separación de ambientes y control del acceso de desarrollo | E16: Ambientes de desarrollo, pruebas y producción con secretos independientes, y desactivación del acceso rápido de administrador en el ambiente productivo. | F16: 3 | G16: Actividad 21: configuración de ambientes | H16: Parcial: la bandera existe y el intento denegado queda en bitácora; falta el perfil de entorno | I16: Importante | J16: Viable

Sheet resumen
A1: Resumen del concepto emitido
A2: Los conteos se calculan solos a partir de las hojas de captura. No escriba en esta hoja.
A4: Concepto | B4: Funcionales y criterios | C4: No funcionales | D4: Total | E4: Participación sobre el total
A5: Viable | B5: =COUNTIF(requerimientos!$J$5:$J$31,$A5) -> 18 | C5: =COUNTIF(no_funcionales!$J$5:$J$16,$A5) -> 11 | D5: =B5+C5 -> 29 | E5: =IFERROR(D5/$D$9,0) -> 0.74358974
A6: Inviable | B6: =COUNTIF(requerimientos!$J$5:$J$31,$A6) -> 0 | C6: =COUNTIF(no_funcionales!$J$5:$J$16,$A6) -> 1 | D6: =B6+C6 -> 1 | E6: =IFERROR(D6/$D$9,0) -> 0.025641026
A7: Replantear | B7: =COUNTIF(requerimientos!$J$5:$J$31,$A7) -> 9 | C7: =COUNTIF(no_funcionales!$J$5:$J$16,$A7) -> 0 | D7: =B7+C7 -> 9 | E7: =IFERROR(D7/$D$9,0) -> 0.23076923
A8: Sin concepto | B8: =27-COUNTA(requerimientos!$J$5:$J$31) -> 0 | C8: =12-COUNTA(no_funcionales!$J$5:$J$16) -> 0 | D8: =B8+C8 -> 0 | E8: =IFERROR(D8/$D$9,0) -> 0
A9: Total | B9: =SUM(B5:B8) -> 27 | C9: =SUM(C5:C8) -> 12 | D9: =SUM(D5:D8) -> 39 | E9: =IFERROR(D9/D9,0) -> 1
A11: Avance de la revisión
A12: Requerimientos con concepto emitido | D12: =D5+D6+D7 -> 39 | E12: =IFERROR(D12/39,0) -> 1 | H12: .
A13: Requerimientos que exigen justificación escrita (inviable o replantear) | D13: =D6+D7 -> 10
A14: Observaciones faltantes en filas de inviable o replantear | D14: =SUMPRODUCT(((requerimientos!$J$5:$J$31="Inviable")+(requerimientos!$J$5:$J$31="Replantear"))*(requerimientos!$K$5:$K$31=""))+SUMPRODUCT(((no_funcionales!$J$5:$J$16="Inviable")+(no_funcionales!$J$5:$J$16="Replantear"))*(no_funcionales!$K$5:$K$16="")) -> 2
A16: Conteo por módulo
A17: Módulo | B17: Viable | C17: Inviable | D17: Replantear | E17: Sin concepto
A18: M0 | B18: =COUNTIFS(requerimientos!$B$5:$B$31,$A18,requerimientos!$J$5:$J$31,"Viable") -> 4 | C18: =COUNTIFS(requerimientos!$B$5:$B$31,$A18,requerimientos!$J$5:$J$31,"Inviable") -> 0 | D18: =COUNTIFS(requerimientos!$B$5:$B$31,$A18,requerimientos!$J$5:$J$31,"Replantear") -> 0 | E18: =COUNTIF(requerimientos!$B$5:$B$31,$A18)-B18-C18-D18 -> 0
A19: M1 | B19: =COUNTIFS(requerimientos!$B$5:$B$31,$A19,requerimientos!$J$5:$J$31,"Viable") -> 3 | C19: =COUNTIFS(requerimientos!$B$5:$B$31,$A19,requerimientos!$J$5:$J$31,"Inviable") -> 0 | D19: =COUNTIFS(requerimientos!$B$5:$B$31,$A19,requerimientos!$J$5:$J$31,"Replantear") -> 1 | E19: =COUNTIF(requerimientos!$B$5:$B$31,$A19)-B19-C19-D19 -> 0
A20: M2 | B20: =COUNTIFS(requerimientos!$B$5:$B$31,$A20,requerimientos!$J$5:$J$31,"Viable") -> 3 | C20: =COUNTIFS(requerimientos!$B$5:$B$31,$A20,requerimientos!$J$5:$J$31,"Inviable") -> 0 | D20: =COUNTIFS(requerimientos!$B$5:$B$31,$A20,requerimientos!$J$5:$J$31,"Replantear") -> 1 | E20: =COUNTIF(requerimientos!$B$5:$B$31,$A20)-B20-C20-D20 -> 0
A21: M3 | B21: =COUNTIFS(requerimientos!$B$5:$B$31,$A21,requerimientos!$J$5:$J$31,"Viable") -> 1 | C21: =COUNTIFS(requerimientos!$B$5:$B$31,$A21,requerimientos!$J$5:$J$31,"Inviable") -> 0 | D21: =COUNTIFS(requerimientos!$B$5:$B$31,$A21,requerimientos!$J$5:$J$31,"Replantear") -> 6 | E21: =COUNTIF(requerimientos!$B$5:$B$31,$A21)-B21-C21-D21 -> 0
A22: M4 | B22: =COUNTIFS(requerimientos!$B$5:$B$31,$A22,requerimientos!$J$5:$J$31,"Viable") -> 4 | C22: =COUNTIFS(requerimientos!$B$5:$B$31,$A22,requerimientos!$J$5:$J$31,"Inviable") -> 0 | D22: =COUNTIFS(requerimientos!$B$5:$B$31,$A22,requerimientos!$J$5:$J$31,"Replantear") -> 0 | E22: =COUNTIF(requerimientos!$B$5:$B$31,$A22)-B22-C22-D22 -> 0
A23: M5 | B23: =COUNTIFS(requerimientos!$B$5:$B$31,$A23,requerimientos!$J$5:$J$31,"Viable") -> 3 | C23: =COUNTIFS(requerimientos!$B$5:$B$31,$A23,requerimientos!$J$5:$J$31,"Inviable") -> 0 | D23: =COUNTIFS(requerimientos!$B$5:$B$31,$A23,requerimientos!$J$5:$J$31,"Replantear") -> 1 | E23: =COUNTIF(requerimientos!$B$5:$B$31,$A23)-B23-C23-D23 -> 0
A24: M0 ingesta · M1 ciclos y clústeres · M2 filtrado · M3 priorización · M4 evaluación y revisión por pares · M5 tableros y alertas

Sheet control de cambios
A1: TABLA DE CONTROL DE CAMBIOS
A2: VERSIÓN | B2: FECHA | C2: DESCRIPCIÓN DEL CAMBIO
A3: 1 | B3: 2026-09-03 | C3: Versión inicial de la matriz de validación de requerimientos, construida sobre la especificación oficial y el cronograma del componente de desarrollo.
B8: ELABORÓ | C8: REVISÓ | D8: AVAL DE CALIDAD | E8: APROBÓ
A9: Nombre y Apellidos:
A10: Cargo y/o actividad: | B10: Líder técnico del componente de desarrollo | C10: Coordinación metodológica de Escaneo de Horizonte | D10: Jefe de gestión del riesgo, calidad y proyectos | E10: Directora Ejecutiva
A11: Fecha:
A12: Firmas:
